odoo/addons/fieldservice_substatus/README.rst
odoo/addons/fieldservice_substatus/__init__.py
odoo/addons/fieldservice_substatus/__manifest__.py
odoo/addons/fieldservice_substatus/data/fsm_stage.xml
odoo/addons/fieldservice_substatus/data/fsm_stage_status.xml
odoo/addons/fieldservice_substatus/data/mail_data.xml
odoo/addons/fieldservice_substatus/i18n/de.po
odoo/addons/fieldservice_substatus/i18n/es.po
odoo/addons/fieldservice_substatus/i18n/es_AR.po
odoo/addons/fieldservice_substatus/i18n/es_CL.po
odoo/addons/fieldservice_substatus/i18n/fieldservice_substatus.pot
odoo/addons/fieldservice_substatus/i18n/it.po
odoo/addons/fieldservice_substatus/i18n/pt_BR.po
odoo/addons/fieldservice_substatus/models/__init__.py
odoo/addons/fieldservice_substatus/models/fsm_order.py
odoo/addons/fieldservice_substatus/models/fsm_stage.py
odoo/addons/fieldservice_substatus/models/fsm_stage_status.py
odoo/addons/fieldservice_substatus/readme/CONFIGURE.rst
odoo/addons/fieldservice_substatus/readme/CONTRIBUTORS.rst
odoo/addons/fieldservice_substatus/readme/CREDITS.rst
odoo/addons/fieldservice_substatus/readme/DESCRIPTION.rst
odoo/addons/fieldservice_substatus/readme/INSTALL.rst
odoo/addons/fieldservice_substatus/readme/ROADMAP.rst
odoo/addons/fieldservice_substatus/readme/USAGE.rst
odoo/addons/fieldservice_substatus/security/ir.model.access.csv
odoo/addons/fieldservice_substatus/static/description/icon.png
odoo/addons/fieldservice_substatus/static/description/index.html
odoo/addons/fieldservice_substatus/tests/__init__.py
odoo/addons/fieldservice_substatus/tests/test_fsm_substatus.py
odoo/addons/fieldservice_substatus/views/fsm_order.xml
odoo/addons/fieldservice_substatus/views/fsm_stage.xml
odoo/addons/fieldservice_substatus/views/fsm_stage_status.xml
odoo14_addon_fieldservice_substatus-14.0.1.1.1.dist-info/METADATA
odoo14_addon_fieldservice_substatus-14.0.1.1.1.dist-info/WHEEL
odoo14_addon_fieldservice_substatus-14.0.1.1.1.dist-info/top_level.txt
odoo14_addon_fieldservice_substatus-14.0.1.1.1.dist-info/RECORD
